[{"t_monotonic": 10117.786160518, "t_since_run_start": 161.62135941500128, "query_migrate": {}}, {"t_monotonic": 10117.989141715, "t_since_run_start": 161.82434061200001, "query_migrate": {"expected-downtime": 300, "status": "active", "setup-time": 2, "total-time": 202, "ram": {"total": 8607571968, "postcopy-requests": 0, "dirty-sync-count": 1, "multifd-bytes": 0, "pages-per-second": 35530, "downtime-bytes": 0, "page-size": 4096, "remaining": 8535318528, "postcopy-bytes": 0, "mbps": 1082.3292, "transferred": 31895057, "dirty-sync-missed-zero-copy": 0, "precopy-bytes": 32021977, "duplicate": 9858, "dirty-pages-rate": 0, "normal-bytes": 31870976, "normal": 7781}}}, {"t_monotonic": 10118.189887163, "t_since_run_start": 162.02508606000083, "query_migrate": {"expected-downtime": 300, "status": "active", "setup-time": 2, "total-time": 403, "ram": {"total": 8607571968, "postcopy-requests": 0, "dirty-sync-count": 1, "multifd-bytes": 0, "pages-per-second": 2045870, "downtime-bytes": 0, "page-size": 4096, "remaining": 7623090176, "postcopy-bytes": 0, "mbps": 1073.75688, "transferred": 62352300, "dirty-sync-missed-zero-copy": 0, "precopy-bytes": 62380173, "duplicate": 225645, "dirty-pages-rate": 0, "normal-bytes": 60231680, "normal": 14705}}}, {"t_monotonic": 10118.39066869, "t_since_run_start": 162.22586758700163, "query_migrate": {"expected-downtime": 300, "status": "active", "setup-time": 2, "total-time": 604, "ram": {"total": 8607571968, "postcopy-requests": 0, "dirty-sync-count": 1, "multifd-bytes": 0, "pages-per-second": 32960, "downtime-bytes": 0, "page-size": 4096, "remaining": 7583506432, "postcopy-bytes": 0, "mbps": 1082.1441599999998, "transferred": 94572334, "dirty-sync-missed-zero-copy": 0, "precopy-bytes": 94571982, "duplicate": 227471, "dirty-pages-rate": 0, "normal-bytes": 92344320, "normal": 22545}}}, {"t_monotonic": 10118.591483047, "t_since_run_start": 162.42668194399994, "query_migrate": {"expected-downtime": 300, "status": "active", "setup-time": 2, "total-time": 805, "ram": {"total": 8607571968, "postcopy-requests": 0, "dirty-sync-count": 1, "multifd-bytes": 0, "pages-per-second": 35220, "downtime-bytes": 0, "page-size": 4096, "remaining": 7532154880, "postcopy-bytes": 0, "mbps": 1082.3068799999999, "transferred": 121258064, "dirty-sync-missed-zero-copy": 0, "precopy-bytes": 121326884, "duplicate": 233501, "dirty-pages-rate": 0, "normal-bytes": 118992896, "normal": 29051}}}, {"t_monotonic": 10118.792430493, "t_since_run_start": 162.62762939000095, "query_migrate": {"expected-downtime": 300, "status": "active", "setup-time": 2, "total-time": 1005, "ram": {"total": 8607571968, "postcopy-requests": 0, "dirty-sync-count": 1, "multifd-bytes": 0, "pages-per-second": 5036020, "downtime-bytes": 0, "page-size": 4096, "remaining": 5352517632, "postcopy-bytes": 0, "mbps": 1077.4180800000001, "transferred": 148417921, "dirty-sync-missed-zero-copy": 0, "precopy-bytes": 148417529, "duplicate": 760194, "dirty-pages-rate": 0, "normal-bytes": 141299712, "normal": 34497}}}, {"t_monotonic": 10118.99332092, "t_since_run_start": 162.8285198170015, "query_migrate": {"expected-downtime": 300, "status": "active", "setup-time": 2, "total-time": 1206, "ram": {"total": 8607571968, "postcopy-requests": 0, "dirty-sync-count": 1, "multifd-bytes": 0, "pages-per-second": 44220, "downtime-bytes": 0, "page-size": 4096, "remaining": 5316026368, "postcopy-bytes": 0, "mbps": 1082.9548799999998, "transferred": 175492378, "dirty-sync-missed-zero-copy": 0, "precopy-bytes": 175491966, "duplicate": 762511, "dirty-pages-rate": 0, "normal-bytes": 168300544, "normal": 41089}}}, {"t_monotonic": 10119.194057077, "t_since_run_start": 163.029255974001, "query_migrate": {"expected-downtime": 300, "status": "active", "setup-time": 2, "total-time": 1407, "ram": {"total": 8607571968, "postcopy-requests": 0, "dirty-sync-count": 1, "multifd-bytes": 0, "pages-per-second": 43800, "downtime-bytes": 0, "page-size": 4096, "remaining": 5283926016, "postcopy-bytes": 0, "mbps": 1082.92464, "transferred": 202557187, "dirty-sync-missed-zero-copy": 0, "precopy-bytes": 202556755, "duplicate": 763756, "dirty-pages-rate": 0, "normal-bytes": 195301376, "normal": 47681}}}, {"t_monotonic": 10119.394940864, "t_since_run_start": 163.23013976100083, "query_migrate": {"expected-downtime": 300, "status": "active", "setup-time": 2, "total-time": 1608, "ram": {"total": 8607571968, "postcopy-requests": 0, "dirty-sync-count": 1, "multifd-bytes": 0, "pages-per-second": 56340, "downtime-bytes": 0, "page-size": 4096, "remaining": 5247254528, "postcopy-bytes": 0, "mbps": 1083.82752, "transferred": 229632040, "dirty-sync-missed-zero-copy": 0, "precopy-bytes": 229631588, "duplicate": 766117, "dirty-pages-rate": 0, "normal-bytes": 222302208, "normal": 54273}}}, {"t_monotonic": 10119.595706761, "t_since_run_start": 163.43090565800048, "query_migrate": {"expected-downtime": 300, "status": "active", "setup-time": 2, "total-time": 1809, "ram": {"total": 8607571968, "postcopy-requests": 0, "dirty-sync-count": 1, "multifd-bytes": 0, "pages-per-second": 33090, "downtime-bytes": 0, "page-size": 4096, "remaining": 5220175872, "postcopy-bytes": 0, "mbps": 1082.15352, "transferred": 256685815, "dirty-sync-missed-zero-copy": 0, "precopy-bytes": 256685343, "duplicate": 766136, "dirty-pages-rate": 0, "normal-bytes": 249303040, "normal": 60865}}}, {"t_monotonic": 10119.796413409, "t_since_run_start": 163.63161230600053, "query_migrate": {"expected-downtime": 300, "status": "active", "setup-time": 2, "total-time": 2009, "ram": {"total": 8607571968, "postcopy-requests": 0, "dirty-sync-count": 1, "multifd-bytes": 0, "pages-per-second": 39640, "downtime-bytes": 0, "page-size": 4096, "remaining": 5182873600, "postcopy-bytes": 0, "mbps": 1082.6251200000002, "transferred": 283762054, "dirty-sync-missed-zero-copy": 0, "precopy-bytes": 283761562, "duplicate": 768651, "dirty-pages-rate": 0, "normal-bytes": 276303872, "normal": 67457}}}, {"t_monotonic": 10119.997179517, "t_since_run_start": 163.83237841400114, "query_migrate": {"expected-downtime": 300, "status": "active", "setup-time": 2, "total-time": 2210, "ram": {"total": 8607571968, "postcopy-requests": 0, "dirty-sync-count": 1, "multifd-bytes": 0, "pages-per-second": 33060, "downtime-bytes": 0, "page-size": 4096, "remaining": 5134184448, "postcopy-bytes": 0, "mbps": 1082.15136, "transferred": 310781413, "dirty-sync-missed-zero-copy": 0, "precopy-bytes": 310780901, "duplicate": 773966, "dirty-pages-rate": 0, "normal-bytes": 303222784, "normal": 74029}}}, {"t_monotonic": 10120.198693967, "t_since_run_start": 164.03389286400125, "query_migrate": {"expected-downtime": 300, "status": "active", "setup-time": 2, "total-time": 2412, "ram": {"total": 8607571968, "postcopy-requests": 0, "dirty-sync-count": 1, "multifd-bytes": 0, "pages-per-second": 32673, "downtime-bytes": 0, "page-size": 4096, "remaining": 5107118080, "postcopy-bytes": 0, "mbps": 1071.432712871287, "transferred": 337835161, "dirty-sync-missed-zero-copy": 0, "precopy-bytes": 337834629, "duplicate": 773982, "dirty-pages-rate": 0, "normal-bytes": 330223616, "normal": 80621}}}, {"t_monotonic": 10120.399443385, "t_since_run_start": 164.234642282001, "query_migrate": {"expected-downtime": 300, "status": "active", "setup-time": 2, "total-time": 2612, "ram": {"total": 8607571968, "postcopy-requests": 0, "dirty-sync-count": 1, "multifd-bytes": 0, "pages-per-second": 33320, "downtime-bytes": 0, "page-size": 4096, "remaining": 5079543808, "postcopy-bytes": 0, "mbps": 1082.17008, "transferred": 364890025, "dirty-sync-missed-zero-copy": 0, "precopy-bytes": 364889473, "duplicate": 774122, "dirty-pages-rate": 0, "normal-bytes": 357224448, "normal": 87213}}}, {"t_monotonic": 10120.600169153, "t_since_run_start": 164.43536805000076, "query_migrate": {"expected-downtime": 300, "status": "active", "setup-time": 2, "total-time": 2813, "ram": {"total": 8607571968, "postcopy-requests": 0, "dirty-sync-count": 1, "multifd-bytes": 0, "pages-per-second": 32980, "downtime-bytes": 0, "page-size": 4096, "remaining": 5048438784, "postcopy-bytes": 0, "mbps": 1082.1456, "transferred": 391952647, "dirty-sync-missed-zero-copy": 0, "precopy-bytes": 391952075, "duplicate": 775124, "dirty-pages-rate": 0, "normal-bytes": 384225280, "normal": 93805}}}, {"t_monotonic": 10120.80093689, "t_since_run_start": 164.63613578700097, "query_migrate": {"expected-downtime": 300, "status": "active", "setup-time": 2, "total-time": 3014, "ram": {"total": 8607571968, "postcopy-requests": 0, "dirty-sync-count": 1, "multifd-bytes": 0, "pages-per-second": 46390, "downtime-bytes": 0, "page-size": 4096, "remaining": 5011218432, "postcopy-bytes": 0, "mbps": 1083.11112, "transferred": 419028706, "dirty-sync-missed-zero-copy": 0, "precopy-bytes": 419028114, "duplicate": 777619, "dirty-pages-rate": 0, "normal-bytes": 411226112, "normal": 100397}}}, {"t_monotonic": 10121.001679278, "t_since_run_start": 164.8368781750014, "query_migrate": {"expected-downtime": 300, "status": "active", "setup-time": 2, "total-time": 3215, "ram": {"total": 8607571968, "postcopy-requests": 0, "dirty-sync-count": 1, "multifd-bytes": 0, "pages-per-second": 32970, "downtime-bytes": 0, "page-size": 4096, "remaining": 4984213504, "postcopy-bytes": 0, "mbps": 1082.1448799999998, "transferred": 446082319, "dirty-sync-missed-zero-copy": 0, "precopy-bytes": 446081707, "duplicate": 777620, "dirty-pages-rate": 0, "normal-bytes": 438226944, "normal": 106989}}}, {"t_monotonic": 10121.202530204, "t_since_run_start": 165.03772910100088, "query_migrate": {"expected-downtime": 300, "status": "active", "setup-time": 2, "total-time": 3415, "ram": {"total": 8607571968, "postcopy-requests": 0, "dirty-sync-count": 1, "multifd-bytes": 0, "pages-per-second": 33720, "downtime-bytes": 0, "page-size": 4096, "remaining": 4956856320, "postcopy-bytes": 0, "mbps": 1082.19888, "transferred": 473136706, "dirty-sync-missed-zero-copy": 0, "precopy-bytes": 473136074, "duplicate": 777707, "dirty-pages-rate": 0, "normal-bytes": 465227776, "normal": 113581}}}, {"t_monotonic": 10121.403223192, "t_since_run_start": 165.23842208899987, "query_migrate": {"expected-downtime": 300, "status": "active", "setup-time": 2, "total-time": 3616, "ram": {"total": 8607571968, "postcopy-requests": 0, "dirty-sync-count": 1, "multifd-bytes": 0, "pages-per-second": 34890, "downtime-bytes": 0, "page-size": 4096, "remaining": 4926722048, "postcopy-bytes": 0, "mbps": 1082.28312, "transferred": 500197195, "dirty-sync-missed-zero-copy": 0, "precopy-bytes": 500196543, "duplicate": 778472, "dirty-pages-rate": 0, "normal-bytes": 492228608, "normal": 120173}}}, {"t_monotonic": 10121.604167508, "t_since_run_start": 165.43936640500033, "query_migrate": {"expected-downtime": 300, "status": "active", "setup-time": 2, "total-time": 3817, "ram": {"total": 8607571968, "postcopy-requests": 0, "dirty-sync-count": 1, "multifd-bytes": 0, "pages-per-second": 33400, "downtime-bytes": 0, "page-size": 4096, "remaining": 4899373056, "postcopy-bytes": 0, "mbps": 1082.17584, "transferred": 527251564, "dirty-sync-missed-zero-copy": 0, "precopy-bytes": 527250892, "duplicate": 778557, "dirty-pages-rate": 0, "normal-bytes": 519229440, "normal": 126765}}}, {"t_monotonic": 10121.804997725, "t_since_run_start": 165.64019662200008, "query_migrate": {"expected-downtime": 300, "status": "active", "setup-time": 2, "total-time": 4018, "ram": {"total": 8607571968, "postcopy-requests": 0, "dirty-sync-count": 1, "multifd-bytes": 0, "pages-per-second": 35750, "downtime-bytes": 0, "page-size": 4096, "remaining": 4871168000, "postcopy-bytes": 0, "mbps": 1082.34504, "transferred": 554307814, "dirty-sync-missed-zero-copy": 0, "precopy-bytes": 554307122, "duplicate": 778851, "dirty-pages-rate": 0, "normal-bytes": 546230272, "normal": 133357}}}, {"t_monotonic": 10122.005769633, "t_since_run_start": 165.8409685300012, "query_migrate": {"expected-downtime": 300, "status": "active", "setup-time": 2, "total-time": 4219, "ram": {"total": 8607571968, "postcopy-requests": 0, "dirty-sync-count": 1, "multifd-bytes": 0, "pages-per-second": 34260, "downtime-bytes": 0, "page-size": 4096, "remaining": 4843618304, "postcopy-bytes": 0, "mbps": 1082.23776, "transferred": 581362624, "dirty-sync-missed-zero-copy": 0, "precopy-bytes": 581361912, "duplicate": 778985, "dirty-pages-rate": 0, "normal-bytes": 573231104, "normal": 139949}}}, {"t_monotonic": 10122.20658464, "t_since_run_start": 166.0417835370008, "query_migrate": {"expected-downtime": 300, "status": "active", "setup-time": 2, "total-time": 4419, "ram": {"total": 8607571968, "postcopy-requests": 0, "dirty-sync-count": 1, "multifd-bytes": 0, "pages-per-second": 33170, "downtime-bytes": 0, "page-size": 4096, "remaining": 4815986688, "postcopy-bytes": 0, "mbps": 1082.15928, "transferred": 608417614, "dirty-sync-missed-zero-copy": 0, "precopy-bytes": 608416882, "duplicate": 779139, "dirty-pages-rate": 0, "normal-bytes": 600231936, "normal": 146541}}}, {"t_monotonic": 10122.407518925, "t_since_run_start": 166.2427178220005, "query_migrate": {"expected-downtime": 300, "status": "active", "setup-time": 2, "total-time": 4620, "ram": {"total": 8607571968, "postcopy-requests": 0, "dirty-sync-count": 1, "multifd-bytes": 0, "pages-per-second": 39700, "downtime-bytes": 0, "page-size": 4096, "remaining": 4786139136, "postcopy-bytes": 0, "mbps": 1082.62944, "transferred": 635477473, "dirty-sync-missed-zero-copy": 0, "precopy-bytes": 635476721, "duplicate": 779834, "dirty-pages-rate": 0, "normal-bytes": 627232768, "normal": 153133}}}, {"t_monotonic": 10122.608352272, "t_since_run_start": 166.44355116900078, "query_migrate": {"expected-downtime": 300, "status": "active", "setup-time": 2, "total-time": 4821, "ram": {"total": 8607571968, "postcopy-requests": 0, "dirty-sync-count": 1, "multifd-bytes": 0, "pages-per-second": 32980, "downtime-bytes": 0, "page-size": 4096, "remaining": 4758921216, "postcopy-bytes": 0, "mbps": 1082.1456, "transferred": 662531554, "dirty-sync-missed-zero-copy": 0, "precopy-bytes": 662530782, "duplicate": 779887, "dirty-pages-rate": 0, "normal-bytes": 654233600, "normal": 159725}}}, {"t_monotonic": 10122.80906085, "t_since_run_start": 166.64425974700134, "query_migrate": {"expected-downtime": 300, "status": "active", "setup-time": 2, "total-time": 5022, "ram": {"total": 8607571968, "postcopy-requests": 0, "dirty-sync-count": 1, "multifd-bytes": 0, "pages-per-second": 33090, "downtime-bytes": 0, "page-size": 4096, "remaining": 4731396096, "postcopy-bytes": 0, "mbps": 1082.15352, "transferred": 689586310, "dirty-sync-missed-zero-copy": 0, "precopy-bytes": 689585518, "duplicate": 780015, "dirty-pages-rate": 0, "normal-bytes": 681234432, "normal": 166317}}}, {"t_monotonic": 10123.009870817, "t_since_run_start": 166.8450697140015, "query_migrate": {"expected-downtime": 300, "status": "active", "setup-time": 2, "total-time": 5223, "ram": {"total": 8607571968, "postcopy-requests": 0, "dirty-sync-count": 1, "multifd-bytes": 0, "pages-per-second": 37200, "downtime-bytes": 0, "page-size": 4096, "remaining": 4702507008, "postcopy-bytes": 0, "mbps": 1082.4494399999999, "transferred": 716644063, "dirty-sync-missed-zero-copy": 0, "precopy-bytes": 716643251, "duplicate": 780476, "dirty-pages-rate": 0, "normal-bytes": 708235264, "normal": 172909}}}, {"t_monotonic": 10123.210709104, "t_since_run_start": 167.0459080010005, "query_migrate": {"expected-downtime": 300, "status": "active", "setup-time": 2, "total-time": 5424, "ram": {"total": 8607571968, "postcopy-requests": 0, "dirty-sync-count": 1, "multifd-bytes": 0, "pages-per-second": 33370, "downtime-bytes": 0, "page-size": 4096, "remaining": 4675330048, "postcopy-bytes": 0, "mbps": 1082.1736799999999, "transferred": 743698054, "dirty-sync-missed-zero-copy": 0, "precopy-bytes": 743697222, "duplicate": 780519, "dirty-pages-rate": 0, "normal-bytes": 735236096, "normal": 179501}}}, {"t_monotonic": 10123.41156795, "t_since_run_start": 167.2467668469999, "query_migrate": {"expected-downtime": 300, "status": "active", "setup-time": 2, "total-time": 5624, "ram": {"total": 8607571968, "postcopy-requests": 0, "dirty-sync-count": 1, "multifd-bytes": 0, "pages-per-second": 33000, "downtime-bytes": 0, "page-size": 4096, "remaining": 4648304640, "postcopy-bytes": 0, "mbps": 1082.14704, "transferred": 770751712, "dirty-sync-missed-zero-copy": 0, "precopy-bytes": 770750860, "duplicate": 780525, "dirty-pages-rate": 0, "normal-bytes": 762236928, "normal": 186093}}}, {"t_monotonic": 10123.612395347, "t_since_run_start": 167.44759424400036, "query_migrate": {"expected-downtime": 300, "status": "active", "setup-time": 2, "total-time": 5825, "ram": {"total": 8607571968, "postcopy-requests": 0, "dirty-sync-count": 1, "multifd-bytes": 0, "pages-per-second": 33040, "downtime-bytes": 0, "page-size": 4096, "remaining": 4621045760, "postcopy-bytes": 0, "mbps": 1082.1499199999998, "transferred": 797805883, "dirty-sync-missed-zero-copy": 0, "precopy-bytes": 797805011, "duplicate": 780588, "dirty-pages-rate": 0, "normal-bytes": 789237760, "normal": 192685}}}, {"t_monotonic": 10123.813229404, "t_since_run_start": 167.64842830100133, "query_migrate": {"expected-downtime": 300, "status": "active", "setup-time": 2, "total-time": 6026, "ram": {"total": 8607571968, "postcopy-requests": 0, "dirty-sync-count": 1, "multifd-bytes": 0, "pages-per-second": 33020, "downtime-bytes": 0, "page-size": 4096, "remaining": 4594003968, "postcopy-bytes": 0, "mbps": 1082.14848, "transferred": 824859577, "dirty-sync-missed-zero-copy": 0, "precopy-bytes": 824858685, "duplicate": 780598, "dirty-pages-rate": 0, "normal-bytes": 816238592, "normal": 199277}}}, {"t_monotonic": 10124.014038571, "t_since_run_start": 167.84923746800087, "query_migrate": {"expected-downtime": 300, "status": "active", "setup-time": 2, "total-time": 6227, "ram": {"total": 8607571968, "postcopy-requests": 0, "dirty-sync-count": 1, "multifd-bytes": 0, "pages-per-second": 32980, "downtime-bytes": 0, "page-size": 4096, "remaining": 4566978560, "postcopy-bytes": 0, "mbps": 1082.1456, "transferred": 851913235, "dirty-sync-missed-zero-copy": 0, "precopy-bytes": 851912323, "duplicate": 780604, "dirty-pages-rate": 0, "normal-bytes": 843239424, "normal": 205869}}}, {"t_monotonic": 10124.214786509, "t_since_run_start": 168.0499854059999, "query_migrate": {"expected-downtime": 300, "status": "active", "setup-time": 2, "total-time": 6428, "ram": {"total": 8607571968, "postcopy-requests": 0, "dirty-sync-count": 1, "multifd-bytes": 0, "pages-per-second": 37010, "downtime-bytes": 0, "page-size": 4096, "remaining": 4536201216, "postcopy-bytes": 0, "mbps": 1082.43576, "transferred": 878975137, "dirty-sync-missed-zero-copy": 0, "precopy-bytes": 878974205, "duplicate": 781526, "dirty-pages-rate": 0, "normal-bytes": 870240256, "normal": 212461}}}, {"t_monotonic": 10124.415736724, "t_since_run_start": 168.2509356210012, "query_migrate": {"expected-downtime": 300, "status": "active", "setup-time": 2, "total-time": 6629, "ram": {"total": 8607571968, "postcopy-requests": 0, "dirty-sync-count": 1, "multifd-bytes": 0, "pages-per-second": 33040, "downtime-bytes": 0, "page-size": 4096, "remaining": 4509159424, "postcopy-bytes": 0, "mbps": 1082.1499199999998, "transferred": 906028831, "dirty-sync-missed-zero-copy": 0, "precopy-bytes": 906027879, "duplicate": 781536, "dirty-pages-rate": 0, "normal-bytes": 897241088, "normal": 219053}}}, {"t_monotonic": 10124.617698391, "t_since_run_start": 168.45289728800162, "query_migrate": {"expected-downtime": 300, "status": "active", "setup-time": 2, "total-time": 6831, "ram": {"total": 8607571968, "postcopy-requests": 0, "dirty-sync-count": 1, "multifd-bytes": 0, "pages-per-second": 33020, "downtime-bytes": 0, "page-size": 4096, "remaining": 4482109440, "postcopy-bytes": 0, "mbps": 1082.14848, "transferred": 933082543, "dirty-sync-missed-zero-copy": 0, "precopy-bytes": 933081571, "duplicate": 781548, "dirty-pages-rate": 0, "normal-bytes": 924241920, "normal": 225645}}}, {"t_monotonic": 10124.818402639, "t_since_run_start": 168.6536015360016, "query_migrate": {"expected-downtime": 300, "status": "active", "setup-time": 2, "total-time": 7031, "ram": {"total": 8607571968, "postcopy-requests": 0, "dirty-sync-count": 1, "multifd-bytes": 0, "pages-per-second": 33020, "downtime-bytes": 0, "page-size": 4096, "remaining": 4455075840, "postcopy-bytes": 0, "mbps": 1082.14848, "transferred": 960136219, "dirty-sync-missed-zero-copy": 0, "precopy-bytes": 960135227, "duplicate": 781556, "dirty-pages-rate": 0, "normal-bytes": 951242752, "normal": 232237}}}, {"t_monotonic": 10125.019065857, "t_since_run_start": 168.85426475400163, "query_migrate": {"expected-downtime": 300, "status": "active", "setup-time": 2, "total-time": 7232, "ram": {"total": 8607571968, "postcopy-requests": 0, "dirty-sync-count": 1, "multifd-bytes": 0, "pages-per-second": 33000, "downtime-bytes": 0, "page-size": 4096, "remaining": 4428050432, "postcopy-bytes": 0, "mbps": 1082.14704, "transferred": 987189877, "dirty-sync-missed-zero-copy": 0, "precopy-bytes": 987188865, "duplicate": 781562, "dirty-pages-rate": 0, "normal-bytes": 978243584, "normal": 238829}}}, {"t_monotonic": 10125.219818995, "t_since_run_start": 169.05501789200025, "query_migrate": {"expected-downtime": 300, "status": "active", "setup-time": 2, "total-time": 7433, "ram": {"total": 8607571968, "postcopy-requests": 0, "dirty-sync-count": 1, "multifd-bytes": 0, "pages-per-second": 32980, "downtime-bytes": 0, "page-size": 4096, "remaining": 4401033216, "postcopy-bytes": 0, "mbps": 1082.1456, "transferred": 1014243517, "dirty-sync-missed-zero-copy": 0, "precopy-bytes": 1014242485, "duplicate": 781566, "dirty-pages-rate": 0, "normal-bytes": 1005244416, "normal": 245421}}}, {"t_monotonic": 10125.420527023, "t_since_run_start": 169.25572592000026, "query_migrate": {"expected-downtime": 300, "status": "active", "setup-time": 2, "total-time": 7633, "ram": {"total": 8607571968, "postcopy-requests": 0, "dirty-sync-count": 1, "multifd-bytes": 0, "pages-per-second": 32960, "downtime-bytes": 0, "page-size": 4096, "remaining": 4374024192, "postcopy-bytes": 0, "mbps": 1082.1441599999998, "transferred": 1041297139, "dirty-sync-missed-zero-copy": 0, "precopy-bytes": 1041296087, "duplicate": 781568, "dirty-pages-rate": 0, "normal-bytes": 1032245248, "normal": 252013}}}, {"t_monotonic": 10125.62130166, "t_since_run_start": 169.45650055700025, "query_migrate": {"expected-downtime": 300, "status": "active", "setup-time": 2, "total-time": 7834, "ram": {"total": 8607571968, "postcopy-requests": 0, "dirty-sync-count": 1, "multifd-bytes": 0, "pages-per-second": 33000, "downtime-bytes": 0, "page-size": 4096, "remaining": 4344274944, "postcopy-bytes": 0, "mbps": 1082.14704, "transferred": 1068356782, "dirty-sync-missed-zero-copy": 0, "precopy-bytes": 1068355710, "duplicate": 782239, "dirty-pages-rate": 0, "normal-bytes": 1059246080, "normal": 258605}}}, {"t_monotonic": 10125.822117597, "t_since_run_start": 169.65731649400004, "query_migrate": {"expected-downtime": 300, "status": "active", "setup-time": 2, "total-time": 8035, "ram": {"total": 8607571968, "postcopy-requests": 0, "dirty-sync-count": 1, "multifd-bytes": 0, "pages-per-second": 32960, "downtime-bytes": 0, "page-size": 4096, "remaining": 4317265920, "postcopy-bytes": 0, "mbps": 1082.1441599999998, "transferred": 1095410404, "dirty-sync-missed-zero-copy": 0, "precopy-bytes": 1095409312, "duplicate": 782241, "dirty-pages-rate": 0, "normal-bytes": 1086246912, "normal": 265197}}}, {"t_monotonic": 10126.022881524, "t_since_run_start": 169.85808042100143, "query_migrate": {"expected-downtime": 300, "status": "active", "setup-time": 2, "total-time": 8236, "ram": {"total": 8607571968, "postcopy-requests": 0, "dirty-sync-count": 1, "multifd-bytes": 0, "pages-per-second": 33000, "downtime-bytes": 0, "page-size": 4096, "remaining": 4290248704, "postcopy-bytes": 0, "mbps": 1082.14704, "transferred": 1122464044, "dirty-sync-missed-zero-copy": 0, "precopy-bytes": 1122462932, "duplicate": 782245, "dirty-pages-rate": 0, "normal-bytes": 1113247744, "normal": 271789}}}, {"t_monotonic": 10126.223600462, "t_since_run_start": 170.05879935900157, "query_migrate": {"expected-downtime": 300, "status": "active", "setup-time": 2, "total-time": 8436, "ram": {"total": 8607571968, "postcopy-requests": 0, "dirty-sync-count": 1, "multifd-bytes": 0, "pages-per-second": 33000, "downtime-bytes": 0, "page-size": 4096, "remaining": 4263206912, "postcopy-bytes": 0, "mbps": 1082.14704, "transferred": 1149517738, "dirty-sync-missed-zero-copy": 0, "precopy-bytes": 1149516606, "duplicate": 782255, "dirty-pages-rate": 0, "normal-bytes": 1140248576, "normal": 278381}}}, {"t_monotonic": 10126.424446699, "t_since_run_start": 170.25964559600106, "query_migrate": {"expected-downtime": 300, "status": "active", "setup-time": 2, "total-time": 8637, "ram": {"total": 8607571968, "postcopy-requests": 0, "dirty-sync-count": 1, "multifd-bytes": 0, "pages-per-second": 32980, "downtime-bytes": 0, "page-size": 4096, "remaining": 4236181504, "postcopy-bytes": 0, "mbps": 1082.1456, "transferred": 1176571396, "dirty-sync-missed-zero-copy": 0, "precopy-bytes": 1176570244, "duplicate": 782261, "dirty-pages-rate": 0, "normal-bytes": 1167249408, "normal": 284973}}}, {"t_monotonic": 10126.626047289, "t_since_run_start": 170.46124618600152, "query_migrate": {"expected-downtime": 300, "status": "active", "setup-time": 2, "total-time": 8839, "ram": {"total": 8607571968, "postcopy-requests": 0, "dirty-sync-count": 1, "multifd-bytes": 0, "pages-per-second": 32980, "downtime-bytes": 0, "page-size": 4096, "remaining": 4209123328, "postcopy-bytes": 0, "mbps": 1082.1456, "transferred": 1203625126, "dirty-sync-missed-zero-copy": 0, "precopy-bytes": 1203623954, "duplicate": 782275, "dirty-pages-rate": 0, "normal-bytes": 1194250240, "normal": 291565}}}, {"t_monotonic": 10126.826753146, "t_since_run_start": 170.6619520430013, "query_migrate": {"expected-downtime": 300, "status": "active", "setup-time": 2, "total-time": 9040, "ram": {"total": 8607571968, "postcopy-requests": 0, "dirty-sync-count": 1, "multifd-bytes": 0, "pages-per-second": 32960, "downtime-bytes": 0, "page-size": 4096, "remaining": 4182122496, "postcopy-bytes": 0, "mbps": 1082.1441599999998, "transferred": 1230678730, "dirty-sync-missed-zero-copy": 0, "precopy-bytes": 1230677538, "duplicate": 782275, "dirty-pages-rate": 0, "normal-bytes": 1221251072, "normal": 298157}}}, {"t_monotonic": 10127.027528624, "t_since_run_start": 170.86272752100012, "query_migrate": {"expected-downtime": 300, "status": "active", "setup-time": 2, "total-time": 9240, "ram": {"total": 8607571968, "postcopy-requests": 0, "dirty-sync-count": 1, "multifd-bytes": 0, "pages-per-second": 32980, "downtime-bytes": 0, "page-size": 4096, "remaining": 4154736640, "postcopy-bytes": 0, "mbps": 1082.1456, "transferred": 1257733180, "dirty-sync-missed-zero-copy": 0, "precopy-bytes": 1257731968, "duplicate": 782369, "dirty-pages-rate": 0, "normal-bytes": 1248251904, "normal": 304749}}}, {"t_monotonic": 10127.228295061, "t_since_run_start": 171.06349395800135, "query_migrate": {"expected-downtime": 300, "status": "active", "setup-time": 2, "total-time": 9441, "ram": {"total": 8607571968, "postcopy-requests": 0, "dirty-sync-count": 1, "multifd-bytes": 0, "pages-per-second": 32960, "downtime-bytes": 0, "page-size": 4096, "remaining": 4127727616, "postcopy-bytes": 0, "mbps": 1082.1441599999998, "transferred": 1284786802, "dirty-sync-missed-zero-copy": 0, "precopy-bytes": 1284785570, "duplicate": 782371, "dirty-pages-rate": 0, "normal-bytes": 1275252736, "normal": 311341}}}, {"t_monotonic": 10127.429044889, "t_since_run_start": 171.26424378600132, "query_migrate": {"expected-downtime": 300, "status": "active", "setup-time": 2, "total-time": 9642, "ram": {"total": 8607571968, "postcopy-requests": 0, "dirty-sync-count": 1, "multifd-bytes": 0, "pages-per-second": 32960, "downtime-bytes": 0, "page-size": 4096, "remaining": 4100702208, "postcopy-bytes": 0, "mbps": 1082.1441599999998, "transferred": 1311840460, "dirty-sync-missed-zero-copy": 0, "precopy-bytes": 1311839208, "duplicate": 782377, "dirty-pages-rate": 0, "normal-bytes": 1302253568, "normal": 317933}}}, {"t_monotonic": 10127.629746027, "t_since_run_start": 171.46494492400052, "query_migrate": {"expected-downtime": 300, "status": "active", "setup-time": 2, "total-time": 9843, "ram": {"total": 8607571968, "postcopy-requests": 0, "dirty-sync-count": 1, "multifd-bytes": 0, "pages-per-second": 33000, "downtime-bytes": 0, "page-size": 4096, "remaining": 4073684992, "postcopy-bytes": 0, "mbps": 1082.14704, "transferred": 1338894100, "dirty-sync-missed-zero-copy": 0, "precopy-bytes": 1338892828, "duplicate": 782381, "dirty-pages-rate": 0, "normal-bytes": 1329254400, "normal": 324525}}}, {"t_monotonic": 10127.830458824, "t_since_run_start": 171.66565772100148, "query_migrate": {"expected-downtime": 300, "status": "active", "setup-time": 2, "total-time": 10043, "ram": {"total": 8607571968, "postcopy-requests": 0, "dirty-sync-count": 1, "multifd-bytes": 0, "pages-per-second": 32980, "downtime-bytes": 0, "page-size": 4096, "remaining": 4046659584, "postcopy-bytes": 0, "mbps": 1082.1456, "transferred": 1365947758, "dirty-sync-missed-zero-copy": 0, "precopy-bytes": 1365946466, "duplicate": 782387, "dirty-pages-rate": 0, "normal-bytes": 1356255232, "normal": 331117}}}, {"t_monotonic": 10128.031118273, "t_since_run_start": 171.8663171700009, "query_migrate": {"expected-downtime": 300, "status": "active", "setup-time": 2, "total-time": 10244, "ram": {"total": 8607571968, "postcopy-requests": 0, "dirty-sync-count": 1, "multifd-bytes": 0, "pages-per-second": 32960, "downtime-bytes": 0, "page-size": 4096, "remaining": 4019634176, "postcopy-bytes": 0, "mbps": 1082.1441599999998, "transferred": 1393001416, "dirty-sync-missed-zero-copy": 0, "precopy-bytes": 1393000104, "duplicate": 782393, "dirty-pages-rate": 0, "normal-bytes": 1383256064, "normal": 337709}}}, {"t_monotonic": 10128.23184854, "t_since_run_start": 172.06704743699993, "query_migrate": {"expected-downtime": 300, "status": "active", "setup-time": 2, "total-time": 10445, "ram": {"total": 8607571968, "postcopy-requests": 0, "dirty-sync-count": 1, "multifd-bytes": 0, "pages-per-second": 33040, "downtime-bytes": 0, "page-size": 4096, "remaining": 3992584192, "postcopy-bytes": 0, "mbps": 1082.1499199999998, "transferred": 1420055128, "dirty-sync-missed-zero-copy": 0, "precopy-bytes": 1420053796, "duplicate": 782405, "dirty-pages-rate": 0, "normal-bytes": 1410256896, "normal": 344301}}}, {"t_monotonic": 10128.432556698, "t_since_run_start": 172.2677555950013, "query_migrate": {"expected-downtime": 300, "status": "active", "setup-time": 2, "total-time": 10645, "ram": {"total": 8607571968, "postcopy-requests": 0, "dirty-sync-count": 1, "multifd-bytes": 0, "pages-per-second": 33040, "downtime-bytes": 0, "page-size": 4096, "remaining": 3965521920, "postcopy-bytes": 0, "mbps": 1082.1499199999998, "transferred": 1447108867, "dirty-sync-missed-zero-copy": 0, "precopy-bytes": 1447107515, "duplicate": 782420, "dirty-pages-rate": 0, "normal-bytes": 1437257728, "normal": 350893}}}, {"t_monotonic": 10128.633214026, "t_since_run_start": 172.46841292300087, "query_migrate": {"expected-downtime": 300, "status": "active", "setup-time": 2, "total-time": 10846, "ram": {"total": 8607571968, "postcopy-requests": 0, "dirty-sync-count": 1, "multifd-bytes": 0, "pages-per-second": 32980, "downtime-bytes": 0, "page-size": 4096, "remaining": 3938250752, "postcopy-bytes": 0, "mbps": 1082.1456, "transferred": 1474163065, "dirty-sync-missed-zero-copy": 0, "precopy-bytes": 1474161693, "duplicate": 782486, "dirty-pages-rate": 0, "normal-bytes": 1464258560, "normal": 357485}}}, {"t_monotonic": 10128.83438345, "t_since_run_start": 172.66958234699996, "query_migrate": {"expected-downtime": 300, "status": "active", "setup-time": 2, "total-time": 11047, "ram": {"total": 8607571968, "postcopy-requests": 0, "dirty-sync-count": 1, "multifd-bytes": 0, "pages-per-second": 33040, "downtime-bytes": 0, "page-size": 4096, "remaining": 3911208960, "postcopy-bytes": 0, "mbps": 1082.1499199999998, "transferred": 1501216759, "dirty-sync-missed-zero-copy": 0, "precopy-bytes": 1501215367, "duplicate": 782496, "dirty-pages-rate": 0, "normal-bytes": 1491259392, "normal": 364077}}}, {"t_monotonic": 10129.035433905, "t_since_run_start": 172.87063280200164, "query_migrate": {"expected-downtime": 300, "status": "active", "setup-time": 2, "total-time": 11248, "ram": {"total": 8607571968, "postcopy-requests": 0, "dirty-sync-count": 1, "multifd-bytes": 0, "pages-per-second": 33000, "downtime-bytes": 0, "page-size": 4096, "remaining": 3884167168, "postcopy-bytes": 0, "mbps": 1082.14704, "transferred": 1528270453, "dirty-sync-missed-zero-copy": 0, "precopy-bytes": 1528269041, "duplicate": 782506, "dirty-pages-rate": 0, "normal-bytes": 1518260224, "normal": 370669}}}, {"t_monotonic": 10129.236283031, "t_since_run_start": 173.07148192800014, "query_migrate": {"expected-downtime": 300, "status": "active", "setup-time": 2, "total-time": 11449, "ram": {"total": 8607571968, "postcopy-requests": 0, "dirty-sync-count": 1, "multifd-bytes": 0, "pages-per-second": 33120, "downtime-bytes": 0, "page-size": 4096, "remaining": 3857084416, "postcopy-bytes": 0, "mbps": 1082.1556799999998, "transferred": 1555324237, "dirty-sync-missed-zero-copy": 0, "precopy-bytes": 1555322805, "duplicate": 782526, "dirty-pages-rate": 0, "normal-bytes": 1545261056, "normal": 377261}}}, {"t_monotonic": 10129.437044349, "t_since_run_start": 173.27224324600138, "query_migrate": {"expected-downtime": 300, "status": "active", "setup-time": 2, "total-time": 11650, "ram": {"total": 8607571968, "postcopy-requests": 0, "dirty-sync-count": 1, "multifd-bytes": 0, "pages-per-second": 33020, "downtime-bytes": 0, "page-size": 4096, "remaining": 3830009856, "postcopy-bytes": 0, "mbps": 1082.14848, "transferred": 1582378003, "dirty-sync-missed-zero-copy": 0, "precopy-bytes": 1582376551, "duplicate": 782544, "dirty-pages-rate": 0, "normal-bytes": 1572261888, "normal": 383853}}}, {"t_monotonic": 10129.637744157, "t_since_run_start": 173.472943054001, "query_migrate": {"expected-downtime": 300, "status": "active", "setup-time": 2, "total-time": 11851, "ram": {"total": 8607571968, "postcopy-requests": 0, "dirty-sync-count": 1, "multifd-bytes": 0, "pages-per-second": 33080, "downtime-bytes": 0, "page-size": 4096, "remaining": 3802902528, "postcopy-bytes": 0, "mbps": 1082.1528, "transferred": 1609431841, "dirty-sync-missed-zero-copy": 0, "precopy-bytes": 1609430369, "duplicate": 782570, "dirty-pages-rate": 0, "normal-bytes": 1599262720, "normal": 390445}}}, {"t_monotonic": 10129.838464635, "t_since_run_start": 173.67366353200123, "query_migrate": {"expected-downtime": 300, "status": "active", "setup-time": 2, "total-time": 12051, "ram": {"total": 8607571968, "postcopy-requests": 0, "dirty-sync-count": 1, "multifd-bytes": 0, "pages-per-second": 33320, "downtime-bytes": 0, "page-size": 4096, "remaining": 3774976000, "postcopy-bytes": 0, "mbps": 1082.17008, "transferred": 1636487479, "dirty-sync-missed-zero-copy": 0, "precopy-bytes": 1636485987, "duplicate": 782796, "dirty-pages-rate": 0, "normal-bytes": 1626263552, "normal": 397037}}}, {"t_monotonic": 10130.039179722, "t_since_run_start": 173.8743786190007, "query_migrate": {"expected-downtime": 300, "status": "active", "setup-time": 2, "total-time": 12252, "ram": {"total": 8607571968, "postcopy-requests": 0, "dirty-sync-count": 1, "multifd-bytes": 0, "pages-per-second": 33200, "downtime-bytes": 0, "page-size": 4096, "remaining": 3747459072, "postcopy-bytes": 0, "mbps": 1082.1614399999999, "transferred": 1663542217, "dirty-sync-missed-zero-copy": 0, "precopy-bytes": 1663540705, "duplicate": 782922, "dirty-pages-rate": 0, "normal-bytes": 1653264384, "normal": 403629}}}, {"t_monotonic": 10130.239984409, "t_since_run_start": 174.07518330600033, "query_migrate": {"expected-downtime": 300, "status": "active", "setup-time": 2, "total-time": 12453, "ram": {"total": 8607571968, "postcopy-requests": 0, "dirty-sync-count": 1, "multifd-bytes": 0, "pages-per-second": 33660, "downtime-bytes": 0, "page-size": 4096, "remaining": 3718123520, "postcopy-bytes": 0, "mbps": 1082.1945600000001, "transferred": 1690600951, "dirty-sync-missed-zero-copy": 0, "precopy-bytes": 1690599419, "duplicate": 783492, "dirty-pages-rate": 0, "normal-bytes": 1680265216, "normal": 410221}}}, {"t_monotonic": 10130.440742977, "t_since_run_start": 174.27594187400064, "query_migrate": {"expected-downtime": 300, "status": "active", "setup-time": 2, "total-time": 12654, "ram": {"total": 8607571968, "postcopy-requests": 0, "dirty-sync-count": 1, "multifd-bytes": 0, "pages-per-second": 35580, "downtime-bytes": 0, "page-size": 4096, "remaining": 3687985152, "postcopy-bytes": 0, "mbps": 1082.3328000000001, "transferred": 1717661449, "dirty-sync-missed-zero-copy": 0, "precopy-bytes": 1717659897, "duplicate": 784258, "dirty-pages-rate": 0, "normal-bytes": 1707266048, "normal": 416813}}}, {"t_monotonic": 10130.641449424, "t_since_run_start": 174.47664832100054, "query_migrate": {"expected-downtime": 300, "status": "active", "setup-time": 2, "total-time": 12854, "ram": {"total": 8607571968, "postcopy-requests": 0, "dirty-sync-count": 1, "multifd-bytes": 0, "pages-per-second": 37040, "downtime-bytes": 0, "page-size": 4096, "remaining": 3657560064, "postcopy-bytes": 0, "mbps": 1082.4379199999998, "transferred": 1744722577, "dirty-sync-missed-zero-copy": 0, "precopy-bytes": 1744721005, "duplicate": 785094, "dirty-pages-rate": 0, "normal-bytes": 1734266880, "normal": 423405}}}, {"t_monotonic": 10130.842349971, "t_since_run_start": 174.6775488680014, "query_migrate": {"expected-downtime": 300, "status": "active", "setup-time": 2, "total-time": 13055, "ram": {"total": 8607571968, "postcopy-requests": 0, "dirty-sync-count": 1, "multifd-bytes": 0, "pages-per-second": 36340, "downtime-bytes": 0, "page-size": 4096, "remaining": 3627429888, "postcopy-bytes": 0, "mbps": 1082.38752, "transferred": 1771783057, "dirty-sync-missed-zero-copy": 0, "precopy-bytes": 1771781465, "duplicate": 785858, "dirty-pages-rate": 0, "normal-bytes": 1761267712, "normal": 429997}}}, {"t_monotonic": 10131.044053589, "t_since_run_start": 174.87925248600004, "query_migrate": {"expected-downtime": 300, "status": "active", "setup-time": 2, "total-time": 13257, "ram": {"total": 8607571968, "postcopy-requests": 0, "dirty-sync-count": 1, "multifd-bytes": 0, "pages-per-second": 37880, "downtime-bytes": 0, "page-size": 4096, "remaining": 3592708096, "postcopy-bytes": 0, "mbps": 1082.4984, "transferred": 1798853626, "dirty-sync-missed-zero-copy": 0, "precopy-bytes": 1798852014, "duplicate": 787743, "dirty-pages-rate": 0, "normal-bytes": 1788268544, "normal": 436589}}}, {"t_monotonic": 10131.244783457, "t_since_run_start": 175.0799823540001, "query_migrate": {"expected-downtime": 300, "status": "active", "setup-time": 2, "total-time": 13458, "ram": {"total": 8607571968, "postcopy-requests": 0, "dirty-sync-count": 1, "multifd-bytes": 0, "pages-per-second": 4253380, "downtime-bytes": 0, "page-size": 4096, "remaining": 161849344, "postcopy-bytes": 0, "mbps": 1074.7944, "transferred": 1825827040, "dirty-sync-missed-zero-copy": 0, "precopy-bytes": 1825825408, "duplicate": 1620609, "dirty-pages-rate": 0, "normal-bytes": 1807708160, "normal": 441335}}}, {"t_monotonic": 10131.445671723, "t_since_run_start": 175.28087062000122, "query_migrate": {"expected-downtime": 300, "status": "active", "setup-time": 2, "total-time": 13659, "ram": {"total": 8607571968, "postcopy-requests": 0, "dirty-sync-count": 1, "multifd-bytes": 0, "pages-per-second": 34170, "downtime-bytes": 0, "page-size": 4096, "remaining": 134352896, "postcopy-bytes": 0, "mbps": 1082.23128, "transferred": 1852881733, "dirty-sync-missed-zero-copy": 0, "precopy-bytes": 1852880081, "duplicate": 1620730, "dirty-pages-rate": 0, "normal-bytes": 1834708992, "normal": 447927}}}, {"t_monotonic": 10131.646593469, "t_since_run_start": 175.48179236600117, "query_migrate": {"expected-downtime": 300, "status": "active", "setup-time": 2, "total-time": 13860, "ram": {"total": 8607571968, "postcopy-requests": 0, "dirty-sync-count": 1, "multifd-bytes": 0, "pages-per-second": 32960, "downtime-bytes": 0, "page-size": 4096, "remaining": 107352064, "postcopy-bytes": 0, "mbps": 1082.1441599999998, "transferred": 1879935337, "dirty-sync-missed-zero-copy": 0, "precopy-bytes": 1879933665, "duplicate": 1620730, "dirty-pages-rate": 0, "normal-bytes": 1861709824, "normal": 454519}}}, {"t_monotonic": 10131.847456946, "t_since_run_start": 175.68265584300025, "query_migrate": {"expected-downtime": 300, "status": "active", "setup-time": 2, "total-time": 14060, "ram": {"total": 8607571968, "postcopy-requests": 0, "dirty-sync-count": 1, "multifd-bytes": 0, "pages-per-second": 32960, "downtime-bytes": 0, "page-size": 4096, "remaining": 80351232, "postcopy-bytes": 0, "mbps": 1082.1441599999998, "transferred": 1906988941, "dirty-sync-missed-zero-copy": 0, "precopy-bytes": 1906987249, "duplicate": 1620730, "dirty-pages-rate": 0, "normal-bytes": 1888710656, "normal": 461111}}}, {"t_monotonic": 10132.048336582, "t_since_run_start": 175.88353547900078, "query_migrate": {"expected-downtime": 300, "status": "active", "setup-time": 2, "total-time": 14261, "ram": {"total": 8607571968, "postcopy-requests": 0, "dirty-sync-count": 1, "multifd-bytes": 0, "pages-per-second": 32960, "downtime-bytes": 0, "page-size": 4096, "remaining": 53350400, "postcopy-bytes": 0, "mbps": 1082.1441599999998, "transferred": 1934042545, "dirty-sync-missed-zero-copy": 0, "precopy-bytes": 1934040833, "duplicate": 1620730, "dirty-pages-rate": 0, "normal-bytes": 1915711488, "normal": 467703}}}, {"t_monotonic": 10132.249956431, "t_since_run_start": 176.08515532800084, "query_migrate": {"expected-downtime": 300, "status": "active", "setup-time": 2, "total-time": 14463, "ram": {"total": 8607571968, "postcopy-requests": 0, "dirty-sync-count": 2, "multifd-bytes": 0, "pages-per-second": 32960, "downtime-bytes": 0, "page-size": 4096, "remaining": 302452736, "postcopy-bytes": 0, "mbps": 1082.1441599999998, "transferred": 1961096149, "dirty-sync-missed-zero-copy": 0, "precopy-bytes": 1961094417, "duplicate": 1620730, "dirty-pages-rate": 4681, "normal-bytes": 1942712320, "normal": 474295}}}, {"t_monotonic": 10132.450834978, "t_since_run_start": 176.28603387500152, "query_migrate": {"expected-downtime": 2351, "status": "active", "setup-time": 2, "total-time": 14664, "ram": {"total": 8607571968, "postcopy-requests": 0, "dirty-sync-count": 2, "multifd-bytes": 0, "pages-per-second": 75090, "downtime-bytes": 0, "page-size": 4096, "remaining": 255950848, "postcopy-bytes": 0, "mbps": 1075.0339199999999, "transferred": 1988065807, "dirty-sync-missed-zero-copy": 0, "precopy-bytes": 1988064055, "duplicate": 1625522, "dirty-pages-rate": 4681, "normal-bytes": 1969586176, "normal": 480856}}}, {"t_monotonic": 10132.651591945, "t_since_run_start": 176.48679084200012, "query_migrate": {"expected-downtime": 2334, "status": "active", "setup-time": 2, "total-time": 14864, "ram": {"total": 8607571968, "postcopy-requests": 0, "dirty-sync-count": 2, "multifd-bytes": 0, "pages-per-second": 39430, "downtime-bytes": 0, "page-size": 4096, "remaining": 225300480, "postcopy-bytes": 0, "mbps": 1082.61, "transferred": 2015127430, "dirty-sync-missed-zero-copy": 0, "precopy-bytes": 2015125658, "duplicate": 1626413, "dirty-pages-rate": 4681, "normal-bytes": 1996587008, "normal": 487448}}}, {"t_monotonic": 10132.852359422, "t_since_run_start": 176.68755831900125, "query_migrate": {"expected-downtime": 2335, "status": "active", "setup-time": 2, "total-time": 15065, "ram": {"total": 8607571968, "postcopy-requests": 0, "dirty-sync-count": 2, "multifd-bytes": 0, "pages-per-second": 33810, "downtime-bytes": 0, "page-size": 4096, "remaining": 197877760, "postcopy-bytes": 0, "mbps": 1082.2053600000002, "transferred": 2042181961, "dirty-sync-missed-zero-copy": 0, "precopy-bytes": 2042180169, "duplicate": 1626516, "dirty-pages-rate": 4681, "normal-bytes": 2023587840, "normal": 494040}}}, {"t_monotonic": 10133.053291558, "t_since_run_start": 176.88849045500137, "query_migrate": {"expected-downtime": 2335, "status": "active", "setup-time": 2, "total-time": 15266, "ram": {"total": 8607571968, "postcopy-requests": 0, "dirty-sync-count": 2, "multifd-bytes": 0, "pages-per-second": 34810, "downtime-bytes": 0, "page-size": 4096, "remaining": 170115072, "postcopy-bytes": 0, "mbps": 1082.27736, "transferred": 2069237239, "dirty-sync-missed-zero-copy": 0, "precopy-bytes": 2069235427, "duplicate": 1626702, "dirty-pages-rate": 4681, "normal-bytes": 2050588672, "normal": 500632}}}, {"t_monotonic": 10133.255919599, "t_since_run_start": 177.0911184960005, "query_migrate": {"expected-downtime": 2335, "status": "active", "setup-time": 2, "total-time": 15469, "ram": {"total": 8607571968, "postcopy-requests": 0, "dirty-sync-count": 2, "multifd-bytes": 0, "pages-per-second": 32990, "downtime-bytes": 0, "page-size": 4096, "remaining": 143101952, "postcopy-bytes": 0, "mbps": 1082.14632, "transferred": 2096290870, "dirty-sync-missed-zero-copy": 0, "precopy-bytes": 2096289038, "duplicate": 1626705, "dirty-pages-rate": 4681, "normal-bytes": 2077589504, "normal": 507224}}}, {"t_monotonic": 10133.456642246, "t_since_run_start": 177.29184114300006, "query_migrate": {"expected-downtime": 2335, "status": "active", "setup-time": 2, "total-time": 15670, "ram": {"total": 8607571968, "postcopy-requests": 0, "dirty-sync-count": 2, "multifd-bytes": 0, "pages-per-second": 33450, "downtime-bytes": 0, "page-size": 4096, "remaining": 115900416, "postcopy-bytes": 0, "mbps": 1082.1794399999999, "transferred": 2123344915, "dirty-sync-missed-zero-copy": 0, "precopy-bytes": 2123343063, "duplicate": 1626754, "dirty-pages-rate": 4681, "normal-bytes": 2104590336, "normal": 513816}}}, {"t_monotonic": 10133.657504693, "t_since_run_start": 177.49270359000002, "query_migrate": {"expected-downtime": 2335, "status": "active", "setup-time": 2, "total-time": 15870, "ram": {"total": 8607571968, "postcopy-requests": 0, "dirty-sync-count": 2, "multifd-bytes": 0, "pages-per-second": 34340, "downtime-bytes": 0, "page-size": 4096, "remaining": 88334336, "postcopy-bytes": 0, "mbps": 1082.24352, "transferred": 2150399761, "dirty-sync-missed-zero-copy": 0, "precopy-bytes": 2150397889, "duplicate": 1626892, "dirty-pages-rate": 4681, "normal-bytes": 2131591168, "normal": 520408}}}, {"t_monotonic": 10133.858051222, "t_since_run_start": 177.69325011900037, "query_migrate": {"expected-downtime": 2335, "status": "active", "setup-time": 2, "total-time": 16071, "ram": {"total": 8607571968, "postcopy-requests": 0, "dirty-sync-count": 2, "multifd-bytes": 0, "pages-per-second": 34540, "downtime-bytes": 0, "page-size": 4096, "remaining": 60686336, "postcopy-bytes": 0, "mbps": 1082.25792, "transferred": 2177454787, "dirty-sync-missed-zero-copy": 0, "precopy-bytes": 2177452895, "duplicate": 1627050, "dirty-pages-rate": 4681, "normal-bytes": 2158592000, "normal": 527000}}}, {"t_monotonic": 10134.05875443, "t_since_run_start": 177.89395332700042, "query_migrate": {"expected-downtime": 2335, "status": "active", "setup-time": 2, "total-time": 16272, "ram": {"total": 8607571968, "postcopy-requests": 0, "dirty-sync-count": 2, "multifd-bytes": 0, "pages-per-second": 32960, "downtime-bytes": 0, "page-size": 4096, "remaining": 33652736, "postcopy-bytes": 0, "mbps": 1082.1441599999998, "transferred": 2204508463, "dirty-sync-missed-zero-copy": 0, "precopy-bytes": 2204506551, "duplicate": 1627058, "dirty-pages-rate": 4681, "normal-bytes": 2185592832, "normal": 533592}}}, {"t_monotonic": 10134.259689196, "t_since_run_start": 178.09488809300092, "query_migrate": {"expected-downtime": 780, "status": "active", "setup-time": 2, "total-time": 16473, "ram": {"total": 8607571968, "postcopy-requests": 0, "dirty-sync-count": 3, "multifd-bytes": 0, "pages-per-second": 37020, "downtime-bytes": 0, "page-size": 4096, "remaining": 75354112, "postcopy-bytes": 0, "mbps": 1082.43648, "transferred": 2231569150, "dirty-sync-missed-zero-copy": 0, "precopy-bytes": 2231567218, "duplicate": 1627845, "dirty-pages-rate": 9242, "normal-bytes": 2212593664, "normal": 540184}}}, {"t_monotonic": 10134.460404913, "t_since_run_start": 178.2956038100001, "query_migrate": {"expected-downtime": 780, "status": "active", "setup-time": 2, "total-time": 16673, "ram": {"total": 8607571968, "postcopy-requests": 0, "dirty-sync-count": 3, "multifd-bytes": 0, "pages-per-second": 33470, "downtime-bytes": 0, "page-size": 4096, "remaining": 47763456, "postcopy-bytes": 0, "mbps": 1082.18088, "transferred": 2258624079, "dirty-sync-missed-zero-copy": 0, "precopy-bytes": 2258622127, "duplicate": 1627989, "dirty-pages-rate": 9242, "normal-bytes": 2239594496, "normal": 546776}}}, {"t_monotonic": 10134.66228665, "t_since_run_start": 178.4974855470009, "query_migrate": {"expected-downtime": 780, "status": "active", "setup-time": 2, "total-time": 16875, "ram": {"total": 8607571968, "postcopy-requests": 0, "dirty-sync-count": 4, "multifd-bytes": 0, "pages-per-second": 34940, "downtime-bytes": 0, "page-size": 4096, "remaining": 39464960, "postcopy-bytes": 0, "mbps": 1082.28672, "transferred": 2285680338, "dirty-sync-missed-zero-copy": 0, "precopy-bytes": 2285678366, "duplicate": 1628284, "dirty-pages-rate": 9242, "normal-bytes": 2266595328, "normal": 553368}}}, {"t_monotonic": 10134.863055428, "t_since_run_start": 178.69825432500147, "query_migrate": {"expected-downtime": 318, "status": "active", "setup-time": 2, "total-time": 17076, "ram": {"total": 8607571968, "postcopy-requests": 0, "dirty-sync-count": 6, "multifd-bytes": 0, "pages-per-second": 32970, "downtime-bytes": 0, "page-size": 4096, "remaining": 26587136, "postcopy-bytes": 0, "mbps": 1082.1448799999998, "transferred": 2312735454, "dirty-sync-missed-zero-copy": 0, "precopy-bytes": 2312733462, "duplicate": 1628452, "dirty-pages-rate": 9242, "normal-bytes": 2293596160, "normal": 559960}}}, {"t_monotonic": 10135.063884654, "t_since_run_start": 178.89908355100124, "query_migrate": {"status": "completed", "setup-time": 2, "downtime": 14, "total-time": 17116, "ram": {"total": 8607571968, "postcopy-requests": 0, "dirty-sync-count": 8, "multifd-bytes": 0, "pages-per-second": 34630, "downtime-bytes": 31956842, "page-size": 4096, "remaining": 0, "postcopy-bytes": 0, "mbps": 1096.2306182073157, "transferred": 2345111350, "dirty-sync-missed-zero-copy": 0, "precopy-bytes": 2312733462, "duplicate": 1628793, "dirty-pages-rate": 0, "normal-bytes": 2325487616, "normal": 567746}}}, {"t_monotonic": 10300.678766457, "t_since_run_start": 344.5139653540009, "query_migrate": {"status": "completed"}}]